setup.py
dist_test_oj/Binomialdistribution.py
dist_test_oj/Gaussiandistribution.py
dist_test_oj/Generaldistribution.py
dist_test_oj/__init__.py
dist_test_oj.egg-info/PKG-INFO
dist_test_oj.egg-info/SOURCES.txt
dist_test_oj.egg-info/dependency_links.txt
dist_test_oj.egg-info/not-zip-safe
dist_test_oj.egg-info/top_level.txt