Metadata-Version: 1.0
Name: dist-test-oj
Version: 0.2
Summary: Gaussian distributions
Home-page: UNKNOWN
Author: OJ Liseth
Author-email: myemail@something.com
License: UNKNOWN
Platform: UNKNOWN
